src/elevator.v
// elevator.v - Individual Elevator FSM
  
module elevator(
    input clk,
    input rst,
    input [1:0] target_floor,    // 2-bit floor target (00=G, 01=1, 10=2, 11=3)
    input move_enable,           // Controller permission to move
    output reg [1:0] current_floor,  // Current floor position
    output reg door_open,        // Door status
    output reg moving_up,        // Movement direction
    output reg moving_down,      // Movement direction
    output reg elevator_busy     // Status indicator
);

    // Floor encoding
    parameter FLOOR_G  = 2'b00;  // Ground floor
    parameter FLOOR_1  = 2'b01;  // First floor  
    parameter FLOOR_2  = 2'b10;  // Second floor
    parameter FLOOR_3  = 2'b11;  // Third floor

    // State encoding
    parameter STATE_IDLE      = 2'b00;
    parameter STATE_MOVING_UP = 2'b01;
    parameter STATE_MOVING_DOWN = 2'b10;
    parameter STATE_DOOR_OPEN = 2'b11;

    reg [1:0] state;
    reg [1:0] next_state;
    reg [2:0] move_timer;      // Timer for floor-to-floor movement
    reg [2:0] door_timer;      // Timer for door operations

    // State transition logic
    always @(posedge clk or posedge rst) begin
        if (rst) begin
            state <= STATE_IDLE;
            current_floor <= FLOOR_G;
            door_open <= 1'b1;     // Doors open at start
            moving_up <= 1'b0;
            moving_down <= 1'b0;
            elevator_busy <= 1'b0;
            move_timer <= 3'b0;
            door_timer <= 3'b0;
        end else begin
            case (state)
                STATE_IDLE: begin
                    door_open <= 1'b1;
                    moving_up <= 1'b0;
                    moving_down <= 1'b0;
                    elevator_busy <= 1'b0;
                    door_timer <= door_timer + 1;
                    
                    if (door_timer >= 3'd3) begin // Door open for 3 cycles
                        if (move_enable && (target_floor != current_floor)) begin
                            state <= (target_floor > current_floor) ? STATE_MOVING_UP : STATE_MOVING_DOWN;
                            move_timer <= 3'b0;
                            elevator_busy <= 1'b1;
                        end
                    end
                end
                
                STATE_MOVING_UP: begin
                    door_open <= 1'b0;
                    moving_up <= 1'b1;
                    moving_down <= 1'b0;
                    elevator_busy <= 1'b1;
                    move_timer <= move_timer + 1;
                    
                    if (move_timer >= 3'd2) begin // Movement takes 2 cycles
                        current_floor <= current_floor + 1; // Move up one floor
                        state <= STATE_DOOR_OPEN;
                        door_timer <= 3'b0;
                    end
                end
                
                STATE_MOVING_DOWN: begin
                    door_open <= 1'b0;
                    moving_up <= 1'b0;
                    moving_down <= 1'b1;
                    elevator_busy <= 1'b1;
                    move_timer <= move_timer + 1;
                    
                    if (move_timer >= 3'd2) begin // Movement takes 2 cycles
                        current_floor <= current_floor - 1; // Move down one floor
                        state <= STATE_DOOR_OPEN;
                        door_timer <= 3'b0;
                    end
                end
                
                STATE_DOOR_OPEN: begin
                    door_open <= 1'b1;
                    moving_up <= 1'b0;
                    moving_down <= 1'b0;
                    elevator_busy <= 1'b1;
                    door_timer <= door_timer + 1;
                    
                    if (door_timer >= 3'd3) begin // Door open for 3 cycles
                        state <= STATE_IDLE;
                        door_timer <= 3'b0;
                    end
                end
            endcase
        end
    end

    // Next state logic (combinational)
    always @(*) begin
        next_state = state;
        case (state)
            STATE_IDLE: begin
                if (move_enable && (target_floor != current_floor)) begin
                    next_state = (target_floor > current_floor) ? STATE_MOVING_UP : STATE_MOVING_DOWN;
                end
            end
            STATE_MOVING_UP: begin
                if (move_timer >= 3'd2) begin
                    next_state = STATE_DOOR_OPEN;
                end
            end
            STATE_MOVING_DOWN: begin
                if (move_timer >= 3'd2) begin
                    next_state = STATE_DOOR_OPEN;
                end
            end
            STATE_DOOR_OPEN: begin
                if (door_timer >= 3'd3) begin
                    next_state = STATE_IDLE;
                end
            end
        endcase
    end

endmodule

src/scheduler.v

// scheduler.v - elevator scheduler

module scheduler(
    input clk,
    input rst,

    input [3:0] floor_requests, // ==> Bitmask: [3]floor3, [2]floor2, [1]floor1, [0]floorG
    input [1:0] elev1_floor, // ==> Elevator 1 current floor
    input elev1_busy, // ==> Elevator 1 busy status
    input elev1_moving_up, // ==> Elevator 1 direction
    input elev1_moving_down, // ==> Elevator 1 direction
    input [1:0] elev2_floor, // ==> Elevator 2 current floor
    input elev2_busy, // ==> Elevator 2 busy status  
    input elev2_moving_up, // ==> Elevator 2 direction
    input elev2_moving_down, // ==> Elevator 2 direction
    
    output reg [1:0] elev1_target, // ==> target floor for elevator 1
    output reg elev1_move_enable,  // ==> move enable for elevator 1
    output reg [1:0] elev2_target, // ==> target floor for elevator 2
    output reg elev2_move_enable,  // ==> move enable for elevator 2
    output reg [3:0] request_ack   // ==> acknowledged requests
);

    reg [3:0] pending_requests;
    reg [1:0] elev1_next_target, elev2_next_target;
    reg elev1_next_enable, elev2_next_enable;
    reg [3:0] next_request_ack;
    
    parameter FLOOR_G = 2'b00;
    parameter FLOOR_1 = 2'b01;
    parameter FLOOR_2 = 2'b10; 
    parameter FLOOR_3 = 2'b11;

    // combinational logic for scheduling
    always @(*) begin
        // default values
        elev1_next_target = elev1_floor;
        elev2_next_target = elev2_floor;
        elev1_next_enable = 1'b0;
        elev2_next_enable = 1'b0;
        next_request_ack = 4'b0000;

        // check each floor
        if (pending_requests[0]) begin // floor G
            if (!elev1_busy) begin
                elev1_next_target = FLOOR_G;
                elev1_next_enable = 1'b1;
                next_request_ack[0] = 1'b1;
            end else if (!elev2_busy) begin
                elev2_next_target = FLOOR_G;
                elev2_next_enable = 1'b1;
                next_request_ack[0] = 1'b1;
            end
        end
        
        if (pending_requests[1]) begin // floor 1
            if (!elev1_busy) begin
                elev1_next_target = FLOOR_1;
                elev1_next_enable = 1'b1;
                next_request_ack[1] = 1'b1;
            end else if (!elev2_busy) begin
                elev2_next_target = FLOOR_1;
                elev2_next_enable = 1'b1;
                next_request_ack[1] = 1'b1;
            end
        end
        
        if (pending_requests[2]) begin // floor 2
            if (!elev1_busy) begin
                elev1_next_target = FLOOR_2;
                elev1_next_enable = 1'b1;
                next_request_ack[2] = 1'b1;
            end else if (!elev2_busy) begin
                elev2_next_target = FLOOR_2;
                elev2_next_enable = 1'b1;
                next_request_ack[2] = 1'b1;
            end
        end
        
        if (pending_requests[3]) begin // floor 3
            if (!elev1_busy) begin
                elev1_next_target = FLOOR_3;
                elev1_next_enable = 1'b1;
                next_request_ack[3] = 1'b1;
            end else if (!elev2_busy) begin
                elev2_next_target = FLOOR_3;
                elev2_next_enable = 1'b1;
                next_request_ack[3] = 1'b1;
            end
        end
    end

    // sequential logic
    always @(posedge clk or posedge rst) begin

        if (rst) begin
            pending_requests <= 4'b0000;
            elev1_target <= FLOOR_G;
            elev2_target <= FLOOR_G;
            elev1_move_enable <= 1'b0;
            elev2_move_enable <= 1'b0;
            request_ack <= 4'b0000;

        end else begin
            pending_requests <= (pending_requests | floor_requests) & ~request_ack;
            elev1_target <= elev1_next_target;
            elev2_target <= elev2_next_target;
            elev1_move_enable <= elev1_next_enable;
            elev2_move_enable <= elev2_next_enable;
            request_ack <= next_request_ack;
        end
    end

endmodule

src/arbiter_priority.v
// arbiter_priority.v - priority arbiter

module arbiter_priority(
    input clk,
    input rst,
    
    input [3:0] floor_requests, // normal floor requests
    input emergency_stop, // emergency stop signal
    input [1:0] priority_floor, // priority floor request 
    input priority_request, // priority request active
    
    output reg [3:0] arbiter_requests, // output requests to scheduler
    output reg emergency_override // emergency override signal
);

    reg emergency_stop_latched;
    reg [1:0] current_priority_floor;
    
    // emergency stop and priority handling
    always @(posedge clk or posedge rst) begin
        
        if (rst) begin
            emergency_stop_latched <= 1'b0;
            emergency_override <= 1'b0;
            current_priority_floor <= 2'b00;
            arbiter_requests <= 4'b0000;
        
        end else begin

            if (emergency_stop) begin
                // emergency situation
                emergency_stop_latched <= 1'b1;
                emergency_override <= 1'b1;
                arbiter_requests <= 4'b0000;
            
            end else if (emergency_stop_latched) begin
                // stay in emergency until system reset
                emergency_override <= 1'b1;
                arbiter_requests <= 4'b0000;
            
            end else if (priority_request) begin
                // priority mode - only serve priority floor
                emergency_override <= 1'b0;
                current_priority_floor <= priority_floor;
                arbiter_requests <= 4'b0000;
                case (priority_floor)
                    2'b00: arbiter_requests[0] <= 1'b1; // Floor G
                    2'b01: arbiter_requests[1] <= 1'b1; // Floor 1
                    2'b10: arbiter_requests[2] <= 1'b1; // Floor 2
                    2'b11: arbiter_requests[3] <= 1'b1; // Floor 3
                endcase
            
            end else begin
                // normal elevator operation
                emergency_override <= 1'b0;
                emergency_stop_latched <= 1'b0;
                arbiter_requests <= floor_requests;
            
            end
        end
    end

endmodule

testbench/tb_scheduler.v
// tb_scheduler.v - testbench for scheduler and arbiter
`timescale 1ns/1ps

module tb_scheduler;

    reg clk, rst;
    reg [3:0] floor_requests;
    reg emergency_stop;
    reg [1:0] priority_floor;
    reg priority_request;
    
    // Elevator 1 signals
    wire [1:0] elev1_target, elev1_floor;
    wire elev1_move_enable, elev1_busy;
    wire elev1_moving_up, elev1_moving_down, elev1_door_open;
    
    // Elevator 2 signals  
    wire [1:0] elev2_target, elev2_floor;
    wire elev2_move_enable, elev2_busy;
    wire elev2_moving_up, elev2_moving_down, elev2_door_open;
    
    wire [3:0] request_ack;
    wire [3:0] arbiter_requests;
    wire emergency_override;

    // instantiating arbiter
    arbiter_priority arbiter (
        .clk(clk),
        .rst(rst),
        .floor_requests(floor_requests),
        .emergency_stop(emergency_stop),
        .priority_floor(priority_floor),
        .priority_request(priority_request),
        .arbiter_requests(arbiter_requests),
        .emergency_override(emergency_override)
    );

    // instantiating scheduler
    scheduler dut (
        .clk(clk),
        .rst(rst),
        .floor_requests(arbiter_requests),
        .elev1_floor(elev1_floor), // FROM elevator 1
        .elev1_busy(elev1_busy), // FROM elevator 1
        .elev1_moving_up(elev1_moving_up), // FROM elevator 1
        .elev1_moving_down(elev1_moving_down), // FROM elevator 1
        .elev2_floor(elev2_floor), // FROM elevator 2
        .elev2_busy(elev2_busy), // FROM elevator 2
        .elev2_moving_up(elev2_moving_up), // FROM elevator 2
        .elev2_moving_down(elev2_moving_down), // FROM elevator 2
        .elev1_target(elev1_target), // TO elevator 1
        .elev1_move_enable(elev1_move_enable), // TO elevator 1
        .elev2_target(elev2_target), // TO elevator 2
        .elev2_move_enable(elev2_move_enable), // TO elevator 2
        .request_ack(request_ack)
    );

    // instantiating elevators 
    elevator elev1 (
        .clk(clk),
        .rst(rst),
        .target_floor(elev1_target), // FROM scheduler
        .move_enable(elev1_move_enable), // FROM scheduler
        .current_floor(elev1_floor), // TO scheduler
        .door_open(elev1_door_open),
        .moving_up(elev1_moving_up), // TO scheduler
        .moving_down(elev1_moving_down), // TO scheduler
        .elevator_busy(elev1_busy) // TO scheduler
    );

    elevator elev2 (
        .clk(clk),
        .rst(rst),
        .target_floor(elev2_target), // FROM scheduler
        .move_enable(elev2_move_enable), // FROM scheduler
        .current_floor(elev2_floor), // TO scheduler
        .door_open(elev2_door_open),
        .moving_up(elev2_moving_up), // TO scheduler
        .moving_down(elev2_moving_down), // TO scheduler
        .elevator_busy(elev2_busy) // TO scheduler
    );

    // clock
    always #5 clk = ~clk;

initial begin

    $display("Dual Elevator System Testbench\n");
    $display("Time\t\tReq\tE1 flr\tE2 flr\tTarget1\tTarget2\tAck");
    
    // initialising
    clk = 0;
    rst = 1;
    floor_requests = 4'b0000;
    emergency_stop = 0;
    priority_floor = 2'b00;
    priority_request = 0;
    #20 rst = 0;
    
    // Test 1: simple request - Floor 2 pressed
    #30 floor_requests = 4'b0100; // Floor 2 request
    #100 floor_requests = 4'b0000; // clear request after elevators respond
    
    #300;
    
    // Test 2: multiple requests
    #30 floor_requests = 4'b1010; // Floors 1 and 3
    #100 floor_requests = 4'b0000;
    
    #400;
    
    // Test 3: priority request
    #30 priority_request = 1;
    priority_floor = 2'b10; // Priority to floor 2
    floor_requests = 4'b0001; // Should be ignored
    #100 priority_request = 0;
    floor_requests = 4'b0000;
    
    #300;
    
    // Test 4: emergency stop
    #30 emergency_stop = 1;
    floor_requests = 4'b1111; // all floors - should be ignored
    #100 emergency_stop = 0;
    floor_requests = 4'b0000;
    
    #300;
    
    $display("\nScheduler Test Complete\n");
    $finish;
end

    // monitor
    always @(posedge clk) begin
        $display("%0t ns\t%b\t%0d\t%0d\t%0d\t%0d\t%b", 
            $realtime, floor_requests, elev1_floor, elev2_floor, 
            elev1_target, elev2_target, request_ack);
    end

    // VCD generation
    initial begin
        $dumpfile("scheduler_system.vcd");
        $dumpvars(0, tb_scheduler);
    end

endmodule

results/waveforms/scheduler_system.vcd
$date
	Sat Nov 08 20:54:42 2025
$end
$version
	Icarus Verilog
$end
$timescale
	1ps
$end
$scope module tb_scheduler $end
$var wire 4 ! arbiter_requests [3:0] $end
$var wire 1 " elev1_busy $end
$var wire 1 # elev1_door_open $end
$var wire 2 $ elev1_floor [1:0] $end
$var wire 1 % elev1_move_enable $end
$var wire 1 & elev1_moving_down $end
$var wire 1 ' elev1_moving_up $end
$var wire 2 ( elev1_target [1:0] $end
$var wire 1 ) elev2_busy $end
$var wire 1 * elev2_door_open $end
$var wire 2 + elev2_floor [1:0] $end
$var wire 1 , elev2_move_enable $end
$var wire 1 - elev2_moving_down $end
$var wire 1 . elev2_moving_up $end
$var wire 2 / elev2_target [1:0] $end
$var wire 1 0 emergency_override $end
$var wire 4 1 request_ack [3:0] $end
$var reg 1 2 clk $end
$var reg 1 3 emergency_stop $end
$var reg 4 4 floor_requests [3:0] $end
$var reg 2 5 priority_floor [1:0] $end
$var reg 1 6 priority_request $end
$var reg 1 7 rst $end
$scope module arbiter $end
$var wire 1 8 clk $end
$var wire 1 9 emergency_stop $end
$var wire 4 : floor_requests [3:0] $end
$var wire 2 ; priority_floor [1:0] $end
$var wire 1 < priority_request $end
$var wire 1 = rst $end
$var reg 4 > arbiter_requests [3:0] $end
$var reg 2 ? current_priority_floor [1:0] $end
$var reg 1 @ emergency_override $end
$var reg 1 A emergency_stop_latched $end
$upscope $end
$scope module dut $end
$var wire 1 8 clk $end
$var wire 1 " elev1_busy $end
$var wire 2 B elev1_floor [1:0] $end
$var wire 1 & elev1_moving_down $end
$var wire 1 ' elev1_moving_up $end
$var wire 1 ) elev2_busy $end
$var wire 2 C elev2_floor [1:0] $end
$var wire 1 - elev2_moving_down $end
$var wire 1 . elev2_moving_up $end
$var wire 4 D floor_requests [3:0] $end
$var wire 1 = rst $end
$var reg 1 E elev1_move_enable $end
$var reg 1 F elev1_next_enable $end
$var reg 2 G elev1_next_target [1:0] $end
$var reg 2 H elev1_target [1:0] $end
$var reg 1 I elev2_move_enable $end
$var reg 1 J elev2_next_enable $end
$var reg 2 K elev2_next_target [1:0] $end
$var reg 2 L elev2_target [1:0] $end
$var reg 4 M next_request_ack [3:0] $end
$var reg 4 N pending_requests [3:0] $end
$var reg 4 O request_ack [3:0] $end
$upscope $end
$scope module elev1 $end
$var wire 1 8 clk $end
$var wire 1 % move_enable $end
$var wire 1 = rst $end
$var wire 2 P target_floor [1:0] $end
$var reg 2 Q current_floor [1:0] $end
$var reg 1 R door_open $end
$var reg 3 S door_timer [2:0] $end
$var reg 1 T elevator_busy $end
$var reg 3 U move_timer [2:0] $end
$var reg 1 V moving_down $end
$var reg 1 W moving_up $end
$var reg 2 X next_state [1:0] $end
$var reg 2 Y state [1:0] $end
$upscope $end
$scope module elev2 $end
$var wire 1 8 clk $end
$var wire 1 , move_enable $end
$var wire 1 = rst $end
$var wire 2 Z target_floor [1:0] $end
$var reg 2 [ current_floor [1:0] $end
$var reg 1 \ door_open $end
$var reg 3 ] door_timer [2:0] $end
$var reg 1 ^ elevator_busy $end
$var reg 3 _ move_timer [2:0] $end
$var reg 1 ` moving_down $end
$var reg 1 a moving_up $end
$var reg 2 b next_state [1:0] $end
$var reg 2 c state [1:0] $end
$upscope $end
$upscope $end
$enddefinitions $end
#0
$dumpvars
b0 c
b0 b
0a
0`
b0 _
0^
b0 ]
1\
b0 [
b0 Z
b0 Y
b0 X
0W
0V
b0 U
0T
b0 S
1R
b0 Q
b0 P
b0 O
b0 N
b0 M
b0 L
b0 K
0J
0I
b0 H
b0 G
0F
0E
b0 D
b0 C
b0 B
0A
0@
b0 ?
b0 >
1=
0<
b0 ;
b0 :
09
08
17
06
b0 5
b0 4
03
02
b0 1
00
b0 /
0.
0-
0,
b0 +
1*
0)
b0 (
0'
0&
0%
b0 $
1#
0"
b0 !
$end
#5000
12
18
#10000
02
08
#15000
12
18
#20000
02
08
07
0=
#25000
b1 ]
b1 S
12
18
#30000
02
08
#35000
b10 S
b10 ]
12
18
#40000
02
08
#45000
b11 ]
b11 S
12
18
#50000
02
08
b100 4
b100 :
#55000
b100 >
b100 !
b100 D
b100 S
b100 ]
12
18
#60000
02
08
#65000
b100 M
1F
b10 G
b101 ]
b101 S
b100 N
12
18
#70000
02
08
#75000
b1 X
b100 O
b100 1
1E
1%
b10 H
b10 (
b10 P
b110 S
b110 ]
12
18
#80000
02
08
#85000
b0 M
0F
b0 G
b111 ]
1T
1"
b1 Y
b111 S
b0 N
12
18
#90000
02
08
#95000
b0 O
b0 1
0E
0%
b0 H
b0 (
b0 P
b1 U
1W
1'
0R
0#
b0 ]
12
18
#100000
02
08
#105000
b11 X
b100 M
1J
b10 K
b1 ]
b10 U
b100 N
12
18
#110000
02
08
#115000
b100 M
1J
b10 K
b1 G
b1 b
b100 O
b100 1
1I
1,
b10 L
b10 /
b10 Z
b0 S
b11 Y
b1 Q
b1 $
b1 B
b11 U
b10 ]
12
18
#120000
02
08
#125000
b1 b
b0 M
0J
b0 K
b11 ]
b1 S
0W
0'
1R
1#
b1 H
b1 (
b1 P
b0 N
12
18
#130000
02
08
#135000
b0 O
b0 1
0I
0,
b0 L
b0 /
b0 Z
b10 S
1^
1)
b1 c
b100 ]
12
18
#140000
02
08
#145000
b0 X
b1 _
1a
1.
0\
0*
b11 S
b100 N
12
18
#150000
02
08
b0 4
b0 :
#155000
b11 b
b0 >
b0 !
b0 D
b0 Y
b0 S
b10 _
12
18
#160000
02
08
#165000
b100 M
1F
b10 G
b1 K
b0 ]
b11 c
b1 [
b1 +
b1 C
b11 _
b1 S
0T
0"
12
18
#170000
02
08
#175000
b1 X
b100 O
b100 1
1E
1%
b1 L
b1 /
b1 Z
b10 H
b10 (
b10 P
b10 S
b1 ]
0a
0.
1\
1*
12
18
#180000
02
08
#185000
b1 X
b0 M
0F
b1 G
b10 ]
b11 S
b0 N
12
18
#190000
02
08
#195000
b0 b
b0 O
b0 1
0E
0%
b1 H
b1 (
b1 P
1T
1"
b0 U
b1 Y
b100 S
b11 ]
12
18
#200000
02
08
#205000
b0 c
b0 ]
b1 U
1W
1'
0R
0#
12
18
#210000
02
08
#215000
b11 X
b10 U
b1 ]
0^
0)
12
18
#220000
02
08
#225000
b10 G
b10 ]
b0 S
b11 Y
b10 Q
b10 $
b10 B
b11 U
12
18
#230000
02
08
#235000
b10 H
b10 (
b10 P
b1 S
0W
0'
1R
1#
b11 ]
12
18
#240000
02
08
#245000
b100 ]
b10 S
12
18
#250000
02
08
#255000
b0 X
b11 S
b101 ]
12
18
#260000
02
08
#265000
b110 ]
b0 Y
b0 S
12
18
#270000
02
08
#275000
b1 S
0T
0"
b111 ]
12
18
#280000
02
08
#285000
b0 ]
b10 S
12
18
#290000
02
08
#295000
b11 S
b1 ]
12
18
#300000
02
08
#305000
b10 ]
b100 S
12
18
#310000
02
08
#315000
b101 S
b11 ]
12
18
#320000
02
08
#325000
b100 ]
b110 S
12
18
#330000
02
08
#335000
b111 S
b101 ]
12
18
#340000
02
08
#345000
b110 ]
b0 S
12
18
#350000
02
08
#355000
b1 S
b111 ]
12
18
#360000
02
08
#365000
b0 ]
b10 S
12
18
#370000
02
08
#375000
b11 S
b1 ]
12
18
#380000
02
08
#385000
b10 ]
b100 S
12
18
#390000
02
08
#395000
b101 S
b11 ]
12
18
#400000
02
08
#405000
b100 ]
b110 S
12
18
#410000
02
08
#415000
b111 S
b101 ]
12
18
#420000
02
08
#425000
b110 ]
b0 S
12
18
#430000
02
08
#435000
b1 S
b111 ]
12
18
#440000
02
08
#445000
b0 ]
b10 S
12
18
#450000
02
08
#455000
b11 S
b1 ]
12
18
#460000
02
08
#465000
b10 ]
b100 S
12
18
#470000
02
08
#475000
b101 S
b11 ]
12
18
#480000
02
08
b1010 4
b1010 :
#485000
b100 ]
b110 S
b1010 >
b1010 !
b1010 D
12
18
#490000
02
08
#495000
b1010 M
1F
b11 G
b1010 N
b111 S
b101 ]
12
18
#500000
02
08
#505000
b1 X
b110 ]
b0 S
b1010 O
b1010 1
1E
1%
b11 H
b11 (
b11 P
12
18
#510000
02
08
#515000
b0 M
0F
b10 G
b1 X
b0 N
b1 S
b111 ]
12
18
#520000
02
08
#525000
b0 X
b0 ]
b10 S
b0 O
b0 1
0E
0%
b10 H
b10 (
b10 P
12
18
#530000
02
08
#535000
b1010 M
1F
b11 G
b1010 N
b11 S
b1 ]
12
18
#540000
02
08
#545000
b1 X
b10 ]
b100 S
b1010 O
b1010 1
1E
1%
b11 H
b11 (
b11 P
12
18
#550000
02
08
#555000
b0 M
0F
b10 G
b0 N
1T
1"
b0 U
b1 Y
b101 S
b11 ]
12
18
#560000
02
08
#565000
b100 ]
b1 U
1W
1'
0R
0#
b0 O
b0 1
0E
0%
b10 H
b10 (
b10 P
12
18
#570000
02
08
#575000
b11 K
b1010 M
1J
b11 X
b1010 N
b10 U
b101 ]
12
18
#580000
02
08
b0 4
b0 :
#585000
b1010 M
1J
b11 K
b11 G
b1 b
b110 ]
b0 S
b11 Y
b11 Q
b11 $
b11 B
b11 U
b1010 O
b1010 1
1I
1,
b11 L
b11 /
b11 Z
b0 >
b0 !
b0 D
12
18
#590000
02
08
#595000
b0 M
0J
b1 K
b11 H
b11 (
b11 P
b0 N
b1 S
0W
0'
1R
1#
1^
1)
b0 _
b1 c
b111 ]
12
18
#600000
02
08
#605000
b1 _
1a
1.
0\
0*
b10 S
b0 O
b0 1
0I
0,
b1 L
b1 /
b1 Z
12
18
#610000
02
08
#615000
b0 X
b11 b
b11 S
b10 _
12
18
#620000
02
08
#625000
b10 K
b0 ]
b11 c
b10 [
b10 +
b10 C
b11 _
b0 Y
b0 S
12
18
#630000
02
08
#635000
b10 L
b10 /
b10 Z
b1 S
0T
0"
b1 ]
0a
0.
1\
1*
12
18
#640000
02
08
#645000
b10 ]
b10 S
12
18
#650000
02
08
#655000
b0 b
b11 S
b11 ]
12
18
#660000
02
08
#665000
b0 c
b0 ]
b100 S
12
18
#670000
02
08
#675000
b101 S
b1 ]
0^
0)
12
18
#680000
02
08
#685000
b10 ]
b110 S
12
18
#690000
02
08
#695000
b111 S
b11 ]
12
18
#700000
02
08
#705000
b100 ]
b0 S
12
18
#710000
02
08
#715000
b1 S
b101 ]
12
18
#720000
02
08
#725000
b110 ]
b10 S
12
18
#730000
02
08
#735000
b11 S
b111 ]
12
18
#740000
02
08
#745000
b0 ]
b100 S
12
18
#750000
02
08
#755000
b101 S
b1 ]
12
18
#760000
02
08
#765000
b10 ]
b110 S
12
18
#770000
02
08
#775000
b111 S
b11 ]
12
18
#780000
02
08
#785000
b100 ]
b0 S
12
18
#790000
02
08
#795000
b1 S
b101 ]
12
18
#800000
02
08
#805000
b110 ]
b10 S
12
18
#810000
02
08
#815000
b11 S
b111 ]
12
18
#820000
02
08
#825000
b0 ]
b100 S
12
18
#830000
02
08
#835000
b101 S
b1 ]
12
18
#840000
02
08
#845000
b10 ]
b110 S
12
18
#850000
02
08
#855000
b111 S
b11 ]
12
18
#860000
02
08
#865000
b100 ]
b0 S
12
18
#870000
02
08
#875000
b1 S
b101 ]
12
18
#880000
02
08
#885000
b110 ]
b10 S
12
18
#890000
02
08
#895000
b11 S
b111 ]
12
18
#900000
02
08
#905000
b0 ]
b100 S
12
18
#910000
02
08
#915000
b101 S
b1 ]
12
18
#920000
02
08
#925000
b10 ]
b110 S
12
18
#930000
02
08
#935000
b111 S
b11 ]
12
18
#940000
02
08
#945000
b100 ]
b0 S
12
18
#950000
02
08
#955000
b1 S
b101 ]
12
18
#960000
02
08
#965000
b110 ]
b10 S
12
18
#970000
02
08
#975000
b11 S
b111 ]
12
18
#980000
02
08
#985000
b0 ]
b100 S
12
18
#990000
02
08
#995000
b101 S
b1 ]
12
18
#1000000
02
08
#1005000
b10 ]
b110 S
12
18
#1010000
02
08
b1 4
b1 :
b10 5
b10 ;
16
1<
#1015000
b100 >
b100 !
b100 D
b10 ?
b111 S
b11 ]
12
18
#1020000
02
08
#1025000
b100 M
1F
b10 G
b100 ]
b0 S
b100 N
b100 >
b100 !
b100 D
12
18
#1030000
02
08
#1035000
b10 X
b100 >
b100 !
b100 D
b100 O
b100 1
1E
1%
b10 H
b10 (
b10 P
b1 S
b101 ]
12
18
#1040000
02
08
#1045000
b10 X
b0 M
0F
b11 G
b110 ]
b10 S
b0 N
b100 >
b100 !
b100 D
12
18
#1050000
02
08
#1055000
b0 X
b100 >
b100 !
b100 D
b0 O
b0 1
0E
0%
b11 H
b11 (
b11 P
b11 S
b111 ]
12
18
#1060000
02
08
#1065000
b100 M
1F
b10 G
b0 ]
b100 S
b100 N
b100 >
b100 !
b100 D
12
18
#1070000
02
08
#1075000
b10 X
b100 >
b100 !
b100 D
b100 O
b100 1
1E
1%
b10 H
b10 (
b10 P
b101 S
b1 ]
12
18
#1080000
02
08
#1085000
b0 M
0F
b11 G
b10 ]
1T
1"
b0 U
b10 Y
b110 S
b0 N
b100 >
b100 !
b100 D
12
18
#1090000
02
08
#1095000
b100 >
b100 !
b100 D
b0 O
b0 1
0E
0%
b11 H
b11 (
b11 P
b1 U
1V
1&
0R
0#
b11 ]
12
18
#1100000
02
08
#1105000
b11 X
b100 M
1J
b100 ]
b10 U
b100 N
b100 >
b100 !
b100 D
12
18
#1110000
02
08
b0 4
b0 :
06
0<
#1115000
b100 M
1J
b10 G
b0 >
b0 !
b0 D
b100 O
b100 1
1I
1,
b0 S
b11 Y
b10 Q
b10 $
b10 B
b11 U
b101 ]
12
18
#1120000
02
08
#1125000
b0 M
0J
b110 ]
b1 S
0V
0&
1R
1#
b10 H
b10 (
b10 P
b0 N
12
18
#1130000
02
08
#1135000
b0 O
b0 1
0I
0,
b10 S
b111 ]
12
18
#1140000
02
08
#1145000
b0 X
b0 ]
b11 S
12
18
#1150000
02
08
#1155000
b0 Y
b0 S
b1 ]
12
18
#1160000
02
08
#1165000
b10 ]
b1 S
0T
0"
12
18
#1170000
02
08
#1175000
b10 S
b11 ]
12
18
#1180000
02
08
#1185000
b100 ]
b11 S
12
18
#1190000
02
08
#1195000
b100 S
b101 ]
12
18
#1200000
02
08
#1205000
b110 ]
b101 S
12
18
#1210000
02
08
#1215000
b110 S
b111 ]
12
18
#1220000
02
08
#1225000
b0 ]
b111 S
12
18
#1230000
02
08
#1235000
b0 S
b1 ]
12
18
#1240000
02
08
#1245000
b10 ]
b1 S
12
18
#1250000
02
08
#1255000
b10 S
b11 ]
12
18
#1260000
02
08
#1265000
b100 ]
b11 S
12
18
#1270000
02
08
#1275000
b100 S
b101 ]
12
18
#1280000
02
08
#1285000
b110 ]
b101 S
12
18
#1290000
02
08
#1295000
b110 S
b111 ]
12
18
#1300000
02
08
#1305000
b0 ]
b111 S
12
18
#1310000
02
08
#1315000
b0 S
b1 ]
12
18
#1320000
02
08
#1325000
b10 ]
b1 S
12
18
#1330000
02
08
#1335000
b10 S
b11 ]
12
18
#1340000
02
08
#1345000
b100 ]
b11 S
12
18
#1350000
02
08
#1355000
b100 S
b101 ]
12
18
#1360000
02
08
#1365000
b110 ]
b101 S
12
18
#1370000
02
08
#1375000
b110 S
b111 ]
12
18
#1380000
02
08
#1385000
b0 ]
b111 S
12
18
#1390000
02
08
#1395000
b0 S
b1 ]
12
18
#1400000
02
08
#1405000
b10 ]
b1 S
12
18
#1410000
02
08
#1415000
b10 S
b11 ]
12
18
#1420000
02
08
#1425000
b100 ]
b11 S
12
18
#1430000
02
08
#1435000
b100 S
b101 ]
12
18
#1440000
02
08
b1111 4
b1111 :
13
19
#1445000
b110 ]
b101 S
1@
10
1A
12
18
#1450000
02
08
#1455000
b110 S
b111 ]
12
18
#1460000
02
08
#1465000
b0 ]
b111 S
12
18
#1470000
02
08
#1475000
b0 S
b1 ]
12
18
#1480000
02
08
#1485000
b10 ]
b1 S
12
18
#1490000
02
08
#1495000
b10 S
b11 ]
12
18
#1500000
02
08
#1505000
b100 ]
b11 S
12
18
#1510000
02
08
#1515000
b100 S
b101 ]
12
18
#1520000
02
08
#1525000
b110 ]
b101 S
12
18
#1530000
02
08
#1535000
b110 S
b111 ]
12
18
#1540000
02
08
b0 4
b0 :
03
09
#1545000
b0 ]
b111 S
12
18
#1550000
02
08
#1555000
b0 S
b1 ]
12
18
#1560000
02
08
#1565000
b10 ]
b1 S
12
18
#1570000
02
08
#1575000
b10 S
b11 ]
12
18
#1580000
02
08
#1585000
b100 ]
b11 S
12
18
#1590000
02
08
#1595000
b100 S
b101 ]
12
18
#1600000
02
08
#1605000
b110 ]
b101 S
12
18
#1610000
02
08
#1615000
b110 S
b111 ]
12
18
#1620000
02
08
#1625000
b0 ]
b111 S
12
18
#1630000
02
08
#1635000
b0 S
b1 ]
12
18
#1640000
02
08
#1645000
b10 ]
b1 S
12
18
#1650000
02
08
#1655000
b10 S
b11 ]
12
18
#1660000
02
08
#1665000
b100 ]
b11 S
12
18
#1670000
02
08
#1675000
b100 S
b101 ]
12
18
#1680000
02
08
#1685000
b110 ]
b101 S
12
18
#1690000
02
08
#1695000
b110 S
b111 ]
12
18
#1700000
02
08
#1705000
b0 ]
b111 S
12
18
#1710000
02
08
#1715000
b0 S
b1 ]
12
18
#1720000
02
08
#1725000
b10 ]
b1 S
12
18
#1730000
02
08
#1735000
b10 S
b11 ]
12
18
#1740000
02
08
#1745000
b100 ]
b11 S
12
18
#1750000
02
08
#1755000
b100 S
b101 ]
12
18
